streamer/__init__.py
streamer/arguments/__init__.py
streamer/arguments/base_arguments.py
streamer/core/__init__.py
streamer/core/buffer.py
streamer/core/demarcation.py
streamer/core/loss.py
streamer/datasets/__init__.py
streamer/datasets/ego4d_dataset.py
streamer/datasets/epic_dataset.py
streamer/loggers/__init__.py
streamer/loggers/audio_logger.py
streamer/loggers/logger.py
streamer/loggers/video_logger.py
streamer/models/__init__.py
streamer/models/inference_model.py
streamer/models/layer.py
streamer/models/model.py
streamer/models/networks.py
streamer/optimizers/__init__.py
streamer/optimizers/streamer_optimizer.py
streamer/utils/__init__.py
streamer/utils/distributed.py
streamer/utils/events.py
streamer/utils/logging.py
streamer_torch-0.0.3.dist-info/LICENSE
streamer_torch-0.0.3.dist-info/METADATA
streamer_torch-0.0.3.dist-info/WHEEL
streamer_torch-0.0.3.dist-info/top_level.txt
streamer_torch-0.0.3.dist-info/RECORD
