Metadata-Version: 2.1
Name: streamer-torch
Version: 0.0.3
Summary: Official implementation of STREAMER, a self-supervised hierarchical event segmentation and representation learning
Home-page: https://ramymounir.com/docs/streamer/
Author: Ramy Mounir
Classifier: Programming Language :: Python :: 3
Classifier: License :: Free for non-commercial use
Requires-Python: >=3.10
License-File: LICENSE
Requires-Dist: torch >=2.0.0
Requires-Dist: ddpw >=5.1.1
Requires-Dist: opencv-python-headless
Requires-Dist: tqdm
Requires-Dist: scikit-video
Requires-Dist: matplotlib
Requires-Dist: torchvision
Requires-Dist: tensorboard
Requires-Dist: pandas
Requires-Dist: moviepy
Requires-Dist: librosa
Requires-Dist: pillow
